pyramid_zcml/__init__.py
pyramid_zcml/_compat.py
pyramid_zcml/configure.zcml
pyramid_zcml/meta.zcml
pyramid_zcml/scaffolds/__init__.py
pyramid_zcml/scaffolds/starter_zcml/CHANGES.txt_tmpl
pyramid_zcml/scaffolds/starter_zcml/README.txt_tmpl
pyramid_zcml/scaffolds/starter_zcml/development.ini_tmpl
pyramid_zcml/scaffolds/starter_zcml/setup.cfg_tmpl
pyramid_zcml/scaffolds/starter_zcml/setup.py_tmpl
pyramid_zcml/scaffolds/starter_zcml/+package+/__init__.py_tmpl
pyramid_zcml/scaffolds/starter_zcml/+package+/configure.zcml
pyramid_zcml/scaffolds/starter_zcml/+package+/resources.py
pyramid_zcml/scaffolds/starter_zcml/+package+/tests.py_tmpl
pyramid_zcml/scaffolds/starter_zcml/+package+/views.py_tmpl
pyramid_zcml/scaffolds/starter_zcml/+package+/static/favicon.ico
pyramid_zcml/scaffolds/starter_zcml/+package+/static/footerbg.png
pyramid_zcml/scaffolds/starter_zcml/+package+/static/headerbg.png
pyramid_zcml/scaffolds/starter_zcml/+package+/static/ie6.css
pyramid_zcml/scaffolds/starter_zcml/+package+/static/middlebg.png
pyramid_zcml/scaffolds/starter_zcml/+package+/static/pylons.css
pyramid_zcml/scaffolds/starter_zcml/+package+/static/pyramid-small.png
pyramid_zcml/scaffolds/starter_zcml/+package+/static/pyramid.png
pyramid_zcml/scaffolds/starter_zcml/+package+/static/transparent.gif
pyramid_zcml/scaffolds/starter_zcml/+package+/templates/mytemplate.pt_tmpl
pyramid_zcml/tests/__init__.py
pyramid_zcml/tests/index.html
pyramid_zcml/tests/test_integration.py
pyramid_zcml/tests/test_units.py
pyramid_zcml/tests/ccbugapp/__init__.py
pyramid_zcml/tests/ccbugapp/configure.zcml
pyramid_zcml/tests/ccbugapp/views.py
pyramid_zcml/tests/defpermbugapp/__init__.py
pyramid_zcml/tests/defpermbugapp/configure.zcml
pyramid_zcml/tests/exceptionviewapp/__init__.py
pyramid_zcml/tests/exceptionviewapp/configure.zcml
pyramid_zcml/tests/exceptionviewapp/models.py
pyramid_zcml/tests/exceptionviewapp/views.py
pyramid_zcml/tests/fixtureapp/__init__.py
pyramid_zcml/tests/fixtureapp/another.zcml
pyramid_zcml-1.2.0.dist-info/METADATA
pyramid_zcml-1.2.0.dist-info/WHEEL
pyramid_zcml-1.2.0.dist-info/entry_points.txt
pyramid_zcml-1.2.0.dist-info/top_level.txt
pyramid_zcml-1.2.0.dist-info/RECORD
