Metadata-Version: 2.1
Name: pyramid-zcml
Version: 1.2.0
Summary: Zope Config Markup Language support for Pyramid
Home-page: http://docs.pylonsproject.org/projects/pyramid_zcml/en/latest/
Author: Chris McDonough, Agendaless Consulting
Author-email: pylons-discuss@googlegroups.com
License: BSD-derived (http://www.repoze.org/LICENSE.txt)
Keywords: web wsgi pylons pyramid
Platform: UNKNOWN
Classifier: Intended Audience :: Developers
Classifier: Programming Language :: Python
Classifier: Programming Language :: Python :: 2
Classifier: Programming Language :: Python :: 2.7
Classifier: Programming Language :: Python :: 3
Classifier: Programming Language :: Python :: 3.4
Classifier: Programming Language :: Python :: 3.5
Classifier: Programming Language :: Python :: 3.6
Classifier: Programming Language :: Python :: 3.7
Classifier: Programming Language :: Python :: Implementation :: CPython
Classifier: Programming Language :: Python :: Implementation :: PyPy
Classifier: Framework :: Pylons
Classifier: Topic :: Internet :: WWW/HTTP
Classifier: Topic :: Internet :: WWW/HTTP :: WSGI
Classifier: License :: Repoze Public License
Requires-Dist: pyramid (>=1.5.0)
Requires-Dist: venusian (>=1.0)
Requires-Dist: zope.configuration (>=3.8.0)
Provides-Extra: docs
Requires-Dist: pylons-sphinx-themes; extra == 'docs'
Requires-Dist: repoze.sphinx.autointerface; extra == 'docs'
Requires-Dist: Sphinx (>=1.3.1); extra == 'docs'
Provides-Extra: testing
Requires-Dist: WebTest; extra == 'testing'
Requires-Dist: nose; extra == 'testing'
Requires-Dist: pyramid-mako; extra == 'testing'
